{
  "bug_id": "JacksonDatabind-108",
  "success": true,
  "error": null,
  "patch": null,
  "project_path": "/tmp/d4j_JacksonDatabind-108_1772715287",
  "patches": [
    [
      {
        "hypothesis": "The refined fix is to remove the null check and handle edge cases properly.",
        "fixed_method": "@Override\npublic <T extends TreeNode> T readTree(JsonParser p) throws IOException {\n    if (!p.hasCurrentToken() || !p.getCurrentToken().isScalarValue()) {\n        return null;\n    } else {\n        return (T) _bindAsTree(p);\n    }\n}",
        "changes": "",
        "diff": "",
        "file_path": "src/main/java/com/fasterxml/jackson/databind/ObjectReader.java",
        "method_name": "readTree",
        "class_name": "ObjectReader",
        "iteration": 1,
        "is_refinement": true,
        "refinement_attempt": 1,
        "original_hypothesis": "",
        "line_numbers": [
          1166,
          1167,
          1168,
          1169,
          1170
        ]
      }
    ]
  ],
  "iterations": 1,
  "monitor_dir": "traces/JacksonDatabind-108/"
}