{
  "bug_id": "JxPath-6",
  "success": true,
  "error": null,
  "patch": null,
  "project_path": "/tmp/d4j_JxPath-6_1772701461",
  "patches": [
    [
      {
        "hypothesis": "the refined patch fixes the root cause of the bug by using a more robust approach to handle different types of objects, including null values and edge cases, and avoids hardcoded values and test-specific logic",
        "fixed_method": "protected boolean equal(EvalContext context, Expression left, Expression right) {\n\nObject l = left.compute(context);\n\nObject r = right.compute(context);\n\n\n\nif (l == null || r == null) {\n\nreturn false;\n\n}\n\n\n\nif (l.getClass().isInstance(InitialContext.class) || l.getClass().isInstance(SelfContext.class)) {\n\nl = ((EvalContext) l).getSingleNodePointer();\n\n}\n\n\n\nif (r.getClass().isInstance(InitialContext.class) || r.getClass().isInstance(SelfContext.class)) {\n\nr = ((EvalContext) r).getSingleNodePointer();\n\n}\n\n\n\nif (l instanceof Collection) {\n\nl = ((Collection) l).iterator();\n\n}\n\n\n\nif (r instanceof Collection) {\n\nr = ((Collection) r).iterator();\n\n}\n\n\n\nif ((l instanceof Iterator) && !(r instanceof Iterator)) {\n\nreturn contains((Iterator) l, r);\n\n}\n\nif (!(l instanceof Iterator) && (r instanceof Iterator)) {\n\nreturn contains((Iterator) r, l);\n\n}\n\nif (l instanceof Iterator && r instanceof Iterator) {\n\nreturn findMatch((Iterator) l, (Iterator) r);\n\n}\n\n\n\nif (l.equals(r)) {\n\nreturn true;\n\n} else {\n\nreturn false;\n\n}\n\n}",
        "changes": "",
        "diff": "",
        "file_path": "src/java/org/apache/commons/jxpath/ri/compiler/CoreOperationCompare.java",
        "method_name": "equal",
        "class_name": "CoreOperationCompare",
        "iteration": 1,
        "is_refinement": true,
        "refinement_attempt": 1,
        "original_hypothesis": "The issue is caused by the incorrect usage of the `instanceof` operator. The `instanceof` operator is used to check if the object is an instance of a specific class. However, in this case, it is used to check if the object is an instance of a specific interface. The `instanceof` operator returns false when the object is an instance of a class that implements the interface, but not when the object is an instance of a class that extends an abstract class that implements the interface. To fix the issue, we need to use the `isInstance()` method of the `Class` object to check if the object is an instance of the interface.",
        "line_numbers": [
          45,
          46,
          47,
          48,
          49,
          50,
          51,
          52,
          53,
          54,
          55,
          56,
          57,
          58,
          59,
          60,
          61,
          62,
          63,
          64,
          65,
          66,
          67,
          68,
          69,
          70,
          71,
          72,
          73,
          74,
          75,
          76,
          77,
          78,
          79,
          80,
          81,
          82,
          83
        ]
      }
    ]
  ],
  "iterations": 1,
  "monitor_dir": "traces/JxPath-6/"
}