{
  "bug_id": "JacksonDatabind-32",
  "success": true,
  "error": null,
  "patch": null,
  "project_path": "/tmp/d4j_JacksonDatabind-32_1771896909",
  "patches": [
    [
      {
        "hypothesis": "The original patches introduce hardcoded handling for the END_OBJECT token that only addresses the specific case of an empty object, leading to overfitting. The solution involves refactoring the methods to handle END_OBJECT in a more generalized way, ensuring that the methods work together correctly and can handle various edge cases involving END_OBJECT tokens.",
        "changes": "- Removed hardcoded size initialization in LinkedHashMap and ArrayList\n+ Added checks for END_OBJECT and END_ARRAY tokens to handle empty structures correctly\n+ Ensured consistent handling of END_OBJECT across both methods",
        "methods": {
          "src/main/java/com/fasterxml/jackson/databind/deser/std/UntypedObjectDeserializer.java::UntypedObjectDeserializer::deserialize::L213": {
            "file_path": "src/main/java/com/fasterxml/jackson/databind/deser/std/UntypedObjectDeserializer.java",
            "method_name": "deserialize",
            "class_name": "UntypedObjectDeserializer",
            "line_numbers": [
              213,
              277
            ],
            "original_code": "\n    @Override\n    public Object deserialize(JsonParser p, DeserializationContext ctxt) throws IOException\n    {\n        switch (p.getCurrentTokenId()) {\n        case JsonTokenId.ID_START_OBJECT:\n        case JsonTokenId.ID_FIELD_NAME:\n            // 28-Oct-2015, tatu: [databind#989] We may also be given END_OBJECT (similar to FIELD_NAME),\n            //    if caller has advanced to the first token of Object, but for empty Object\n            if (_mapDeserializer != null) {\n                return _mapDeserializer.deserialize(p, ctxt);\n            }\n            return mapObject(p, ctxt);\n        case JsonTokenId.ID_START_ARRAY:\n            if (ctxt.isEnabled(DeserializationFeature.USE_JAVA_ARRAY_FOR_JSON_ARRAY)) {\n                return mapArrayToArray(p, ctxt);\n            }\n            if (_listDeserializer != null) {\n                return _listDeserializer.deserialize(p, ctxt);\n            }\n            return mapArray(p, ctxt);\n        case JsonTokenId.ID_EMBEDDED_OBJECT:\n            return p.getEmbeddedObject();\n        case JsonTokenId.ID_STRING:\n            if (_stringDeserializer != null) {\n                return _stringDeserializer.deserialize(p, ctxt);\n            }\n            return p.getText();\n\n        case JsonTokenId.ID_NUMBER_INT:\n            if (_numberDeserializer != null) {\n                return _numberDeserializer.deserialize(p, ctxt);\n            }\n            /* Caller may want to get all integral values returned as {@link java.math.BigInteger},\n             * or {@link java.lang.Long} for consistency\n             */\n            if (ctxt.hasSomeOfFeatures(F_MASK_INT_COERCIONS)) {\n                return _coerceIntegral(p, ctxt);\n            }\n            return p.getNumberValue(); // should be optimal, whatever it is\n\n        case JsonTokenId.ID_NUMBER_FLOAT:\n            if (_numberDeserializer != null) {\n                return _numberDeserializer.deserialize(p, ctxt);\n            }\n            /* [JACKSON-72]: need to allow overriding the behavior regarding\n             *   which type to use\n             */\n            if (ctxt.isEnabled(DeserializationFeature.USE_BIG_DECIMAL_FOR_FLOATS)) {\n                return p.getDecimalValue();\n            }\n            return p.getDoubleValue();\n\n        case JsonTokenId.ID_TRUE:\n            return Boolean.TRUE;\n        case JsonTokenId.ID_FALSE:\n            return Boolean.FALSE;\n\n        case JsonTokenId.ID_NULL: // should not get this but...\n            return null;\n\n//        case JsonTokenId.ID_END_ARRAY: // invalid\n        default:\n        }\n        throw ctxt.mappingException(Object.class);\n    }\n",
            "fixed_method": "    @Override\n    public Object deserialize(JsonParser p, DeserializationContext ctxt) throws IOException {\n        switch (p.getCurrentTokenId()) {\n        case JsonTokenId.ID_START_OBJECT:\n        case JsonTokenId.ID_FIELD_NAME:\n            // Handle empty objects correctly\n            if (p.nextToken() == JsonToken.END_OBJECT) {\n                return new LinkedHashMap<String, Object>();\n            }\n            if (_mapDeserializer != null) {\n                return _mapDeserializer.deserialize(p, ctxt);\n            }\n            return mapObject(p, ctxt);\n        case JsonTokenId.ID_START_ARRAY:\n            if (ctxt.isEnabled(DeserializationFeature.USE_JAVA_ARRAY_FOR_JSON_ARRAY)) {\n                return mapArrayToArray(p, ctxt);\n            }\n            if (_listDeserializer != null) {\n                return _listDeserializer.deserialize(p, ctxt);\n            }\n            return mapArray(p, ctxt);\n        case JsonTokenId.ID_EMBEDDED_OBJECT:\n            return p.getEmbeddedObject();\n        case JsonTokenId.ID_STRING:\n            if (_stringDeserializer != null) {\n                return _stringDeserializer.deserialize(p, ctxt);\n            }\n            return p.getText();\n        case JsonTokenId.ID_NUMBER_INT:\n            if (_numberDeserializer != null) {\n                return _numberDeserializer.deserialize(p, ctxt);\n            }\n            if (ctxt.hasSomeOfFeatures(F_MASK_INT_COERCIONS)) {\n                return _coerceIntegral(p, ctxt);\n            }\n            return p.getNumberValue();\n        case JsonTokenId.ID_NUMBER_FLOAT:\n            if (_numberDeserializer != null) {\n                return _numberDeserializer.deserialize(p, ctxt);\n            }\n            if (ctxt.isEnabled(DeserializationFeature.USE_BIG_DECIMAL_FOR_FLOATS)) {\n                return p.getDecimalValue();\n            }\n            return p.getDoubleValue();\n        case JsonTokenId.ID_TRUE:\n            return Boolean.TRUE;\n        case JsonTokenId.ID_FALSE:\n            return Boolean.FALSE;\n        case JsonTokenId.ID_NULL:\n            return null;\n        case JsonTokenId.ID_END_OBJECT:\n            return new LinkedHashMap<String, Object>();\n        default:\n        }\n        throw ctxt.mappingException(Object.class);\n    }",
            "attempt": 1
          },
          "src/main/java/com/fasterxml/jackson/databind/deser/std/UntypedObjectDeserializer.java::UntypedObjectDeserializer::deserialize::L483": {
            "file_path": "src/main/java/com/fasterxml/jackson/databind/deser/std/UntypedObjectDeserializer.java",
            "method_name": "deserialize",
            "class_name": "UntypedObjectDeserializer",
            "line_numbers": [
              483,
              542
            ],
            "original_code": "\n        @Override\n        public Object deserialize(JsonParser p, DeserializationContext ctxt) throws IOException\n        {\n            switch (p.getCurrentTokenId()) {\n            case JsonTokenId.ID_START_OBJECT:\n                {\n                    JsonToken t = p.nextToken();\n                    if (t == JsonToken.END_OBJECT) {\n                        return new LinkedHashMap<String,Object>(2);\n                    }\n                }\n            case JsonTokenId.ID_FIELD_NAME:\n                return mapObject(p, ctxt);\n            case JsonTokenId.ID_START_ARRAY:\n                {\n                    JsonToken t = p.nextToken();\n                    if (t == JsonToken.END_ARRAY) { // and empty one too\n                        if (ctxt.isEnabled(DeserializationFeature.USE_JAVA_ARRAY_FOR_JSON_ARRAY)) {\n                            return NO_OBJECTS;\n                        }\n                        return new ArrayList<Object>(2);\n                    }\n                }\n                if (ctxt.isEnabled(DeserializationFeature.USE_JAVA_ARRAY_FOR_JSON_ARRAY)) {\n                    return mapArrayToArray(p, ctxt);\n                }\n                return mapArray(p, ctxt);\n            case JsonTokenId.ID_EMBEDDED_OBJECT:\n                return p.getEmbeddedObject();\n            case JsonTokenId.ID_STRING:\n                return p.getText();\n\n            case JsonTokenId.ID_NUMBER_INT:\n                if (ctxt.hasSomeOfFeatures(F_MASK_INT_COERCIONS)) {\n                    return _coerceIntegral(p, ctxt);\n                }\n                return p.getNumberValue(); // should be optimal, whatever it is\n\n            case JsonTokenId.ID_NUMBER_FLOAT:\n                if (ctxt.isEnabled(DeserializationFeature.USE_BIG_DECIMAL_FOR_FLOATS)) {\n                    return p.getDecimalValue();\n                }\n                return Double.valueOf(p.getDoubleValue());\n\n            case JsonTokenId.ID_TRUE:\n                return Boolean.TRUE;\n            case JsonTokenId.ID_FALSE:\n                return Boolean.FALSE;\n\n            case JsonTokenId.ID_NULL: // should not get this but...\n                return null;\n\n                // 28-Oct-2015, tatu: [databind#989] We may also be given END_OBJECT (similar to FIELD_NAME),\n                //    if caller has advanced to the first token of Object, but for empty Object\n\n            //case JsonTokenId.ID_END_ARRAY: // invalid\n            default:\n                throw ctxt.mappingException(Object.class);\n            }\n        }\n",
            "fixed_method": "    @Override\n    public Object deserialize(JsonParser p, DeserializationContext ctxt) throws IOException {\n        switch (p.getCurrentTokenId()) {\n        case JsonTokenId.ID_START_OBJECT:\n            JsonToken t = p.nextToken();\n            if (t == JsonToken.END_OBJECT) {\n                return new LinkedHashMap<String, Object>();\n            }\n            return mapObject(p, ctxt);\n        case JsonTokenId.ID_FIELD_NAME:\n            return mapObject(p, ctxt);\n        case JsonTokenId.ID_START_ARRAY:\n            t = p.nextToken();\n            if (t == JsonToken.END_ARRAY) {\n                if (ctxt.isEnabled(DeserializationFeature.USE_JAVA_ARRAY_FOR_JSON_ARRAY)) {\n                    return NO_OBJECTS;\n                }\n                return new ArrayList<Object>();\n            }\n            if (ctxt.isEnabled(DeserializationFeature.USE_JAVA_ARRAY_FOR_JSON_ARRAY)) {\n                return mapArrayToArray(p, ctxt);\n            }\n            return mapArray(p, ctxt);\n        case JsonTokenId.ID_EMBEDDED_OBJECT:\n            return p.getEmbeddedObject();\n        case JsonTokenId.ID_STRING:\n            return p.getText();\n        case JsonTokenId.ID_NUMBER_INT:\n            if (ctxt.hasSomeOfFeatures(F_MASK_INT_COERCIONS)) {\n                return _coerceIntegral(p, ctxt);\n            }\n            return p.getNumberValue();\n        case JsonTokenId.ID_NUMBER_FLOAT:\n            if (ctxt.isEnabled(DeserializationFeature.USE_BIG_DECIMAL_FOR_FLOATS)) {\n                return p.getDecimalValue();\n            }\n            return Double.valueOf(p.getDoubleValue());\n        case JsonTokenId.ID_TRUE:\n            return Boolean.TRUE;\n        case JsonTokenId.ID_FALSE:\n            return Boolean.FALSE;\n        case JsonTokenId.ID_NULL:\n            return null;\n        case JsonTokenId.ID_END_OBJECT:\n            return new LinkedHashMap<String, Object>();\n        default:\n            throw ctxt.mappingException(Object.class);\n        }\n    }",
            "attempt": 1
          }
        },
        "is_multi_method": true,
        "is_refinement": true,
        "refinement_attempt": 1
      },
      {
        "hypothesis": "The original patches introduce hardcoded values and limited token handling, leading to overfitting. To address this, we will remove hardcoded values, handle more general cases, and ensure both methods work together correctly.",
        "changes": "- Removed hardcoded sizes for LinkedHashMap and ArrayList\n+ Used default constructors for LinkedHashMap and ArrayList\n+ Ensured consistent handling of END_OBJECT and END_ARRAY tokens",
        "methods": {
          "src/main/java/com/fasterxml/jackson/databind/deser/std/UntypedObjectDeserializer.java::UntypedObjectDeserializer::deserialize::L213": {
            "file_path": "src/main/java/com/fasterxml/jackson/databind/deser/std/UntypedObjectDeserializer.java",
            "method_name": "deserialize",
            "class_name": "UntypedObjectDeserializer",
            "line_numbers": [
              213,
              277
            ],
            "original_code": "\n    @Override\n    public Object deserialize(JsonParser p, DeserializationContext ctxt) throws IOException\n    {\n        switch (p.getCurrentTokenId()) {\n        case JsonTokenId.ID_START_OBJECT:\n        case JsonTokenId.ID_FIELD_NAME:\n            // 28-Oct-2015, tatu: [databind#989] We may also be given END_OBJECT (similar to FIELD_NAME),\n            //    if caller has advanced to the first token of Object, but for empty Object\n            if (_mapDeserializer != null) {\n                return _mapDeserializer.deserialize(p, ctxt);\n            }\n            return mapObject(p, ctxt);\n        case JsonTokenId.ID_START_ARRAY:\n            if (ctxt.isEnabled(DeserializationFeature.USE_JAVA_ARRAY_FOR_JSON_ARRAY)) {\n                return mapArrayToArray(p, ctxt);\n            }\n            if (_listDeserializer != null) {\n                return _listDeserializer.deserialize(p, ctxt);\n            }\n            return mapArray(p, ctxt);\n        case JsonTokenId.ID_EMBEDDED_OBJECT:\n            return p.getEmbeddedObject();\n        case JsonTokenId.ID_STRING:\n            if (_stringDeserializer != null) {\n                return _stringDeserializer.deserialize(p, ctxt);\n            }\n            return p.getText();\n\n        case JsonTokenId.ID_NUMBER_INT:\n            if (_numberDeserializer != null) {\n                return _numberDeserializer.deserialize(p, ctxt);\n            }\n            /* Caller may want to get all integral values returned as {@link java.math.BigInteger},\n             * or {@link java.lang.Long} for consistency\n             */\n            if (ctxt.hasSomeOfFeatures(F_MASK_INT_COERCIONS)) {\n                return _coerceIntegral(p, ctxt);\n            }\n            return p.getNumberValue(); // should be optimal, whatever it is\n\n        case JsonTokenId.ID_NUMBER_FLOAT:\n            if (_numberDeserializer != null) {\n                return _numberDeserializer.deserialize(p, ctxt);\n            }\n            /* [JACKSON-72]: need to allow overriding the behavior regarding\n             *   which type to use\n             */\n            if (ctxt.isEnabled(DeserializationFeature.USE_BIG_DECIMAL_FOR_FLOATS)) {\n                return p.getDecimalValue();\n            }\n            return p.getDoubleValue();\n\n        case JsonTokenId.ID_TRUE:\n            return Boolean.TRUE;\n        case JsonTokenId.ID_FALSE:\n            return Boolean.FALSE;\n\n        case JsonTokenId.ID_NULL: // should not get this but...\n            return null;\n\n//        case JsonTokenId.ID_END_ARRAY: // invalid\n        default:\n        }\n        throw ctxt.mappingException(Object.class);\n    }\n",
            "fixed_method": "    @Override\n    public Object deserialize(JsonParser p, DeserializationContext ctxt) throws IOException {\n        switch (p.getCurrentTokenId()) {\n        case JsonTokenId.ID_START_OBJECT:\n        case JsonTokenId.ID_FIELD_NAME:\n            if (_mapDeserializer != null) {\n                return _mapDeserializer.deserialize(p, ctxt);\n            }\n            return mapObject(p, ctxt);\n        case JsonTokenId.ID_START_ARRAY:\n            if (ctxt.isEnabled(DeserializationFeature.USE_JAVA_ARRAY_FOR_JSON_ARRAY)) {\n                return mapArrayToArray(p, ctxt);\n            }\n            if (_listDeserializer != null) {\n                return _listDeserializer.deserialize(p, ctxt);\n            }\n            return mapArray(p, ctxt);\n        case JsonTokenId.ID_EMBEDDED_OBJECT:\n            return p.getEmbeddedObject();\n        case JsonTokenId.ID_STRING:\n            if (_stringDeserializer != null) {\n                return _stringDeserializer.deserialize(p, ctxt);\n            }\n            return p.getText();\n        case JsonTokenId.ID_NUMBER_INT:\n            if (_numberDeserializer != null) {\n                return _numberDeserializer.deserialize(p, ctxt);\n            }\n            if (ctxt.hasSomeOfFeatures(F_MASK_INT_COERCIONS)) {\n                return _coerceIntegral(p, ctxt);\n            }\n            return p.getNumberValue();\n        case JsonTokenId.ID_NUMBER_FLOAT:\n            if (_numberDeserializer != null) {\n                return _numberDeserializer.deserialize(p, ctxt);\n            }\n            if (ctxt.isEnabled(DeserializationFeature.USE_BIG_DECIMAL_FOR_FLOATS)) {\n                return p.getDecimalValue();\n            }\n            return p.getDoubleValue();\n        case JsonTokenId.ID_TRUE:\n            return Boolean.TRUE;\n        case JsonTokenId.ID_FALSE:\n            return Boolean.FALSE;\n        case JsonTokenId.ID_NULL:\n            return null;\n        case JsonTokenId.ID_END_OBJECT:\n            return new LinkedHashMap<String, Object>();\n        case JsonTokenId.ID_END_ARRAY:\n            if (ctxt.isEnabled(DeserializationFeature.USE_JAVA_ARRAY_FOR_JSON_ARRAY)) {\n                return NO_OBJECTS;\n            }\n            return new ArrayList<Object>();\n        default:\n        }\n        throw ctxt.mappingException(Object.class);\n    }",
            "attempt": 1
          },
          "src/main/java/com/fasterxml/jackson/databind/deser/std/UntypedObjectDeserializer.java::UntypedObjectDeserializer::deserialize::L483": {
            "file_path": "src/main/java/com/fasterxml/jackson/databind/deser/std/UntypedObjectDeserializer.java",
            "method_name": "deserialize",
            "class_name": "UntypedObjectDeserializer",
            "line_numbers": [
              483,
              542
            ],
            "original_code": "\n        @Override\n        public Object deserialize(JsonParser p, DeserializationContext ctxt) throws IOException\n        {\n            switch (p.getCurrentTokenId()) {\n            case JsonTokenId.ID_START_OBJECT:\n                {\n                    JsonToken t = p.nextToken();\n                    if (t == JsonToken.END_OBJECT) {\n                        return new LinkedHashMap<String,Object>(2);\n                    }\n                }\n            case JsonTokenId.ID_FIELD_NAME:\n                return mapObject(p, ctxt);\n            case JsonTokenId.ID_START_ARRAY:\n                {\n                    JsonToken t = p.nextToken();\n                    if (t == JsonToken.END_ARRAY) { // and empty one too\n                        if (ctxt.isEnabled(DeserializationFeature.USE_JAVA_ARRAY_FOR_JSON_ARRAY)) {\n                            return NO_OBJECTS;\n                        }\n                        return new ArrayList<Object>(2);\n                    }\n                }\n                if (ctxt.isEnabled(DeserializationFeature.USE_JAVA_ARRAY_FOR_JSON_ARRAY)) {\n                    return mapArrayToArray(p, ctxt);\n                }\n                return mapArray(p, ctxt);\n            case JsonTokenId.ID_EMBEDDED_OBJECT:\n                return p.getEmbeddedObject();\n            case JsonTokenId.ID_STRING:\n                return p.getText();\n\n            case JsonTokenId.ID_NUMBER_INT:\n                if (ctxt.hasSomeOfFeatures(F_MASK_INT_COERCIONS)) {\n                    return _coerceIntegral(p, ctxt);\n                }\n                return p.getNumberValue(); // should be optimal, whatever it is\n\n            case JsonTokenId.ID_NUMBER_FLOAT:\n                if (ctxt.isEnabled(DeserializationFeature.USE_BIG_DECIMAL_FOR_FLOATS)) {\n                    return p.getDecimalValue();\n                }\n                return Double.valueOf(p.getDoubleValue());\n\n            case JsonTokenId.ID_TRUE:\n                return Boolean.TRUE;\n            case JsonTokenId.ID_FALSE:\n                return Boolean.FALSE;\n\n            case JsonTokenId.ID_NULL: // should not get this but...\n                return null;\n\n                // 28-Oct-2015, tatu: [databind#989] We may also be given END_OBJECT (similar to FIELD_NAME),\n                //    if caller has advanced to the first token of Object, but for empty Object\n\n            //case JsonTokenId.ID_END_ARRAY: // invalid\n            default:\n                throw ctxt.mappingException(Object.class);\n            }\n        }\n",
            "fixed_method": "    @Override\n    public Object deserialize(JsonParser p, DeserializationContext ctxt) throws IOException {\n        switch (p.getCurrentTokenId()) {\n        case JsonTokenId.ID_START_OBJECT:\n            JsonToken t = p.nextToken();\n            if (t == JsonToken.END_OBJECT) {\n                return new LinkedHashMap<String, Object>();\n            }\n            return mapObject(p, ctxt);\n        case JsonTokenId.ID_FIELD_NAME:\n            return mapObject(p, ctxt);\n        case JsonTokenId.ID_START_ARRAY:\n            JsonToken arrayToken = p.nextToken();\n            if (arrayToken == JsonToken.END_ARRAY) {\n                if (ctxt.isEnabled(DeserializationFeature.USE_JAVA_ARRAY_FOR_JSON_ARRAY)) {\n                    return NO_OBJECTS;\n                }\n                return new ArrayList<Object>();\n            }\n            if (ctxt.isEnabled(DeserializationFeature.USE_JAVA_ARRAY_FOR_JSON_ARRAY)) {\n                return mapArrayToArray(p, ctxt);\n            }\n            return mapArray(p, ctxt);\n        case JsonTokenId.ID_EMBEDDED_OBJECT:\n            return p.getEmbeddedObject();\n        case JsonTokenId.ID_STRING:\n            return p.getText();\n        case JsonTokenId.ID_NUMBER_INT:\n            if (ctxt.hasSomeOfFeatures(F_MASK_INT_COERCIONS)) {\n                return _coerceIntegral(p, ctxt);\n            }\n            return p.getNumberValue();\n        case JsonTokenId.ID_NUMBER_FLOAT:\n            if (ctxt.isEnabled(DeserializationFeature.USE_BIG_DECIMAL_FOR_FLOATS)) {\n                return p.getDecimalValue();\n            }\n            return p.getDoubleValue();\n        case JsonTokenId.ID_TRUE:\n            return Boolean.TRUE;\n        case JsonTokenId.ID_FALSE:\n            return Boolean.FALSE;\n        case JsonTokenId.ID_NULL:\n            return null;\n        case JsonTokenId.ID_END_OBJECT:\n            return new LinkedHashMap<String, Object>();\n        case JsonTokenId.ID_END_ARRAY:\n            if (ctxt.isEnabled(DeserializationFeature.USE_JAVA_ARRAY_FOR_JSON_ARRAY)) {\n                return NO_OBJECTS;\n            }\n            return new ArrayList<Object>();\n        default:\n            throw ctxt.mappingException(Object.class);\n        }\n    }",
            "attempt": 1
          }
        },
        "is_multi_method": true,
        "is_refinement": true,
        "refinement_attempt": 1
      }
    ]
  ],
  "iterations": 1,
  "monitor_dir": "traces/JacksonDatabind-32/"
}