{
  "bug_id": "Math-97",
  "success": true,
  "error": null,
  "patch": null,
  "project_path": "/tmp/d4j_Math-97_1771878263",
  "patches": [
    [
      {
        "hypothesis": "The refined fix will address overfitting by checking if either endpoint is close to zero within a specified tolerance, rather than only checking for exact zero. This ensures the method handles general cases and edge scenarios correctly.",
        "fixed_method": "public double solve(double min, double max) throws MaxIterationsExceededException, FunctionEvaluationException {\n    clearResult();\n    verifyInterval(min, max);\n    \n    double ret = Double.NaN;\n    \n    double yMin = f.value(min);\n    double yMax = f.value(max);\n    \n    // Verify bracketing\n    double sign = yMin * yMax;\n    if (sign > 0) {\n        // check if either value is close to a zero\n        if (Math.abs(yMin) < getAbsoluteAccuracy()) {\n            return min;\n        } else if (Math.abs(yMax) < getAbsoluteAccuracy()) {\n            return max;\n        }\n        // neither value is close to zero and min and max do not bracket root.\n        throw new IllegalArgumentException\n        (\"Function values at endpoints do not have different signs.\" +\n                 \"  Endpoints: [\" + min + \",\" + max + \"]\" + \n                 \"  Values: [\" + yMin + \",\" + yMax + \"]\");\n    } else if (sign == 0) {\n        // one of the endpoints is exactly zero\n        return (yMin == 0) ? min : max;\n    } else {\n        // solve using only the first endpoint as initial guess\n        ret = solve(min, yMin, max, yMax, min, yMin);\n        // either min or max is a root\n    }\n\n    return ret;\n}",
        "diff": " ",
        "file_path": "src/java/org/apache/commons/math/analysis/BrentSolver.java",
        "method_name": "solve",
        "class_name": "BrentSolver",
        "iteration": 1,
        "is_refinement": true,
        "refinement_attempt": 1,
        "original_hypothesis": "The bug is caused by the incorrect verification of the interval endpoints. The current implementation checks if the function values at the endpoints have opposite signs, which is correct. However, it does not handle cases where one of the endpoints is exactly zero, which should also be considered a valid root.",
        "line_numbers": [
          125,
          126,
          127,
          128,
          129,
          130,
          131,
          132,
          133,
          134,
          135,
          136,
          137,
          138,
          139,
          140,
          141,
          142,
          143,
          144,
          145,
          146,
          147,
          148,
          149,
          150,
          151,
          152
        ]
      },
      {
        "hypothesis": "The refined fix addresses the overfitting by correctly handling the edge case where the product of yMin and yMax is exactly zero. It checks if either yMin or yMax is exactly zero and returns the corresponding endpoint if true. This ensures that the method behaves correctly for all edge cases without being specific to test inputs.",
        "fixed_method": "public double solve(double min, double max) throws MaxIterationsExceededException, FunctionEvaluationException {\n\n    clearResult();\n    verifyInterval(min, max);\n    \n    double ret = Double.NaN;\n    \n    double yMin = f.value(min);\n    double yMax = f.value(max);\n    \n    // Verify bracketing\n    double sign = yMin * yMax;\n    if (sign >= 0) {\n        // Check if either value is exactly zero\n        if (yMin == 0) {\n            return min;\n        }\n        if (yMax == 0) {\n            return max;\n        }\n        // Check if either value is close to zero\n        if (Math.abs(yMin) < getAbsoluteAccuracy()) {\n            return min;\n        }\n        if (Math.abs(yMax) < getAbsoluteAccuracy()) {\n            return max;\n        }\n        // Neither value is close to zero and min and max do not bracket root.\n        throw new IllegalArgumentException\n        (\"Function values at endpoints do not have different signs.\" +\n                 \"  Endpoints: [\" + min + \",\" + max + \"]\" + \n                 \"  Values: [\" + yMin + \",\" + yMax + \"]\");\n    } else {\n        // Solve using only the first endpoint as initial guess\n        ret = solve(min, yMin, max, yMax, min, yMin);\n        // Either min or max is a root\n    }\n\n    return ret;\n}",
        "diff": " ",
        "file_path": "src/java/org/apache/commons/math/analysis/BrentSolver.java",
        "method_name": "solve",
        "class_name": "BrentSolver",
        "iteration": 1,
        "is_refinement": true,
        "refinement_attempt": 1,
        "original_hypothesis": "The bug is caused by the verification of the interval which checks if the function values at the endpoints have opposite signs. The test expects the method to handle cases where one of the endpoints is a root without throwing an exception.",
        "line_numbers": [
          125,
          126,
          127,
          128,
          129,
          130,
          131,
          132,
          133,
          134,
          135,
          136,
          137,
          138,
          139,
          140,
          141,
          142,
          143,
          144,
          145,
          146,
          147,
          148,
          149,
          150,
          151,
          152
        ]
      },
      {
        "hypothesis": "The refined fix will address overfitting by using a tolerance level to determine if the function values at the endpoints are close enough to zero, rather than checking for exact zero. This will make the solution more robust and handle edge cases where the function values are very close to zero but not exactly zero.",
        "fixed_method": "public double solve(double min, double max) throws MaxIterationsExceededException, FunctionEvaluationException {\n    clearResult();\n    verifyInterval(min, max);\n    \n    double ret = Double.NaN;\n    \n    double yMin = f.value(min);\n    double yMax = f.value(max);\n    \n    // Define a tolerance level\n    double tolerance = getAbsoluteAccuracy();\n    \n    // Verify bracketing with tolerance\n    if (Math.abs(yMin) <= tolerance) {\n        return min;\n    } else if (Math.abs(yMax) <= tolerance) {\n        return max;\n    } else {\n        double sign = yMin * yMax;\n        if (sign >= 0) {\n            // neither value is close to zero and min and max do not bracket root.\n            throw new IllegalArgumentException\n            (\"Function values at endpoints do not have different signs.\" +\n                    \"  Endpoints: [\" + min + \",\" + max + \"]\" + \n                    \"  Values: [\" + yMin + \",\" + yMax + \"]\");\n        } else {\n            // solve using only the first endpoint as initial guess\n            ret = solve(min, yMin, max, yMax, min, yMin);\n            // either min or max is a root\n        }\n    }\n\n    return ret;\n}",
        "diff": " ",
        "file_path": "src/java/org/apache/commons/math/analysis/BrentSolver.java",
        "method_name": "solve",
        "class_name": "BrentSolver",
        "iteration": 1,
        "is_refinement": true,
        "refinement_attempt": 1,
        "original_hypothesis": "The bug arises because the method checks if the function values at the endpoints have opposite signs before solving. If either endpoint is exactly zero, the product of the function values will be zero, which does not satisfy the condition for opposite signs. The fix involves checking if either endpoint is zero and returning it as the root if true.",
        "line_numbers": [
          125,
          126,
          127,
          128,
          129,
          130,
          131,
          132,
          133,
          134,
          135,
          136,
          137,
          138,
          139,
          140,
          141,
          142,
          143,
          144,
          145,
          146,
          147,
          148,
          149,
          150,
          151,
          152
        ]
      }
    ]
  ],
  "iterations": 1,
  "monitor_dir": "traces/Math-97/"
}