{
  "bug_id": "Cli-35",
  "success": true,
  "error": null,
  "patch": null,
  "project_path": "/tmp/d4j_Cli-35_1771986278",
  "patches": [
    [
      {
        "hypothesis": "The refined fix will handle both exact and prefix matches correctly without overfitting. It will prioritize exact matches by checking for them first and then collecting all prefix matches if no exact match is found. Additionally, it will include null checks to handle edge cases.",
        "fixed_method": "public List<String> getMatchingOptions(String opt)\n{\n    if (opt == null) {\n        return Collections.emptyList();\n    }\n    \n    opt = Util.stripLeadingHyphens(opt);\n    \n    List<String> matchingOpts = new ArrayList<String>();\n    boolean exactMatchFound = false;\n\n    for (String longOpt : longOpts.keySet())\n    {\n        if (longOpt.equals(opt)) {\n            matchingOpts.clear();\n            matchingOpts.add(longOpt);\n            exactMatchFound = true;\n            break;\n        }\n    }\n    \n    if (!exactMatchFound) {\n        for (String longOpt : longOpts.keySet()) {\n            if (longOpt.startsWith(opt)) {\n                matchingOpts.add(longOpt);\n            }\n        }\n    }\n    \n    return matchingOpts;\n}",
        "diff": " ",
        "file_path": "src/main/java/org/apache/commons/cli/Options.java",
        "method_name": "getMatchingOptions",
        "class_name": "Options",
        "iteration": 1,
        "is_refinement": true,
        "refinement_attempt": 1,
        "original_hypothesis": "The issue arises because the method returns multiple options that start with the given prefix, leading to an AmbiguousOptionException. To fix this, we need to ensure that only exact matches are returned if they exist, before returning options that just start with the prefix.",
        "line_numbers": [
          233,
          234,
          235,
          236,
          237,
          238,
          239,
          240,
          241,
          242,
          243,
          244,
          245,
          246,
          247,
          248,
          249,
          250
        ]
      },
      {
        "hypothesis": "The refined fix ensures that both exact and prefix matches are handled correctly without prioritizing one over the other. It also includes null checks and handles case sensitivity appropriately.",
        "fixed_method": "public List<String> getMatchingOptions(String opt)\n{\n    if (opt == null) {\n        return Collections.emptyList();\n    }\n    \n    opt = Util.stripLeadingHyphens(opt);\n    \n    List<String> matchingOpts = new ArrayList<String>();\n\n    // Collect all options that start with the prefix\n    for (String longOpt : longOpts.keySet())\n    {\n        if (longOpt.toLowerCase().startsWith(opt.toLowerCase()))\n        {\n            matchingOpts.add(longOpt);\n        }\n    }\n    \n    // Check for an exact match to prioritize it if present\n    if (matchingOpts.contains(opt)) {\n        matchingOpts.clear();\n        matchingOpts.add(opt);\n    }\n    \n    return matchingOpts;\n}",
        "diff": " ",
        "file_path": "src/main/java/org/apache/commons/cli/Options.java",
        "method_name": "getMatchingOptions",
        "class_name": "Options",
        "iteration": 1,
        "is_refinement": true,
        "refinement_attempt": 1,
        "original_hypothesis": "The bug occurs because the method returns multiple options that start with the given prefix, causing ambiguity. To fix this, we should first check for an exact match before adding options that just start with the prefix.",
        "line_numbers": [
          233,
          234,
          235,
          236,
          237,
          238,
          239,
          240,
          241,
          242,
          243,
          244,
          245,
          246,
          247,
          248,
          249,
          250
        ]
      },
      {
        "hypothesis": "The issue arises because the method returns multiple options that start with the given prefix, causing ambiguity. To fix this, we should check for an exact match first and return it immediately if found.",
        "changes": "+ if (longOpt.equals(opt)) { return Collections.singletonList(longOpt); }",
        "fixed_method": "public List<String> getMatchingOptions(String opt)\n{\n    opt = Util.stripLeadingHyphens(opt);\n    \n    List<String> matchingOpts = new ArrayList<String>();\n\n    // Check for an exact match first\n    for (String longOpt : longOpts.keySet()) {\n        if (longOpt.equals(opt)) {\n            return Collections.singletonList(longOpt);\n        }\n    }\n\n    // for a partial match return all options starting with the prefix\n    for (String longOpt : longOpts.keySet())\n    {\n        if (longOpt.startsWith(opt))\n        {\n            matchingOpts.add(longOpt);\n        }\n    }\n    \n    return matchingOpts;\n}",
        "diff": "+ if (longOpt.equals(opt)) { return Collections.singletonList(longOpt); }",
        "file_path": "src/main/java/org/apache/commons/cli/Options.java",
        "method_name": "getMatchingOptions",
        "class_name": "Options",
        "iteration": 1,
        "is_multi_method": false,
        "line_numbers": [
          233,
          234,
          235,
          236,
          237,
          238,
          239,
          240,
          241,
          242,
          243,
          244,
          245,
          246,
          247,
          248,
          249,
          250
        ],
        "original_code": "/**\n* Returns the options with a long name starting with the name specified.\n*\n* @param opt the partial name of the option\n* @return the options matching the partial name specified, or an empty list if none matches\n* @since 1.3\n*/\npublic List<String> getMatchingOptions(String opt)\n{\n    opt = Util.stripLeadingHyphens(opt);\n    \n    List<String> matchingOpts = new ArrayList<String>();\n\n    // for a perfect match return the single option only\n\n    for (String longOpt : longOpts.keySet())\n    {\n        if (longOpt.startsWith(opt))\n        {\n            matchingOpts.add(longOpt);\n        }\n    }\n    \n    return matchingOpts;\n}"
      },
      {
        "hypothesis": "The refined fix ensures that the method correctly handles cases where multiple options share the same prefix by collecting all matching options and only returning a single option if there is an exact match. This avoids overfitting by maintaining the original intent of returning all matching options unless an exact match is found.",
        "fixed_method": "public List<String> getMatchingOptions(String opt)\n{\n    if (opt == null) {\n        return Collections.emptyList();\n    }\n    \n    opt = Util.stripLeadingHyphens(opt);\n    \n    List<String> matchingOpts = new ArrayList<String>();\n    String exactMatch = null;\n\n    for (String longOpt : longOpts.keySet())\n    {\n        if (longOpt.equals(opt)) {\n            exactMatch = longOpt;\n        } else if (longOpt.startsWith(opt))\n        {\n            matchingOpts.add(longOpt);\n        }\n    }\n    \n    if (exactMatch != null) {\n        return Collections.singletonList(exactMatch);\n    }\n    \n    return matchingOpts;\n}",
        "diff": " ",
        "file_path": "src/main/java/org/apache/commons/cli/Options.java",
        "method_name": "getMatchingOptions",
        "class_name": "Options",
        "iteration": 1,
        "is_refinement": true,
        "refinement_attempt": 1,
        "original_hypothesis": "The bug is caused by the method returning multiple options that start with the given prefix, leading to an AmbiguousOptionException. The fix is to modify the method to return only an exact match if it exists, otherwise return all matching options.",
        "line_numbers": [
          233,
          234,
          235,
          236,
          237,
          238,
          239,
          240,
          241,
          242,
          243,
          244,
          245,
          246,
          247,
          248,
          249,
          250
        ]
      },
      {
        "hypothesis": "The refined fix will first check for an exact match and return it immediately if found. If no exact match is found, it will continue to collect and return all options starting with the given prefix. This ensures that the method behaves correctly for both exact and prefix matches while avoiding overfitting.",
        "fixed_method": "public List<String> getMatchingOptions(String opt)\n{\n    if (opt == null) {\n        return Collections.emptyList();\n    }\n    \n    opt = Util.stripLeadingHyphens(opt);\n    \n    List<String> matchingOpts = new ArrayList<String>();\n    boolean exactMatchFound = false;\n    \n    for (String longOpt : longOpts.keySet())\n    {\n        if (longOpt.equals(opt))\n        {\n            matchingOpts.add(longOpt);\n            exactMatchFound = true;\n            break; // Exit loop after finding the exact match\n        }\n    }\n    \n    if (!exactMatchFound)\n    {\n        for (String longOpt : longOpts.keySet())\n        {\n            if (longOpt.startsWith(opt))\n            {\n                matchingOpts.add(longOpt);\n            }\n        }\n    }\n    \n    return matchingOpts;\n}",
        "diff": " ",
        "file_path": "src/main/java/org/apache/commons/cli/Options.java",
        "method_name": "getMatchingOptions",
        "class_name": "Options",
        "iteration": 1,
        "is_refinement": true,
        "refinement_attempt": 1,
        "original_hypothesis": "The issue arises because the method returns multiple options that start with the given prefix, leading to ambiguity when an exact match is expected. The fix should ensure that if there's an exact match, it returns only that option.",
        "line_numbers": [
          233,
          234,
          235,
          236,
          237,
          238,
          239,
          240,
          241,
          242,
          243,
          244,
          245,
          246,
          247,
          248,
          249,
          250
        ]
      },
      {
        "hypothesis": "The bug occurs because the method returns multiple options that start with the given prefix, causing an AmbiguousOptionException when there is more than one match. The fix should ensure that an exact match is prioritized and returned alone if it exists.",
        "changes": "+ if (longOpt.equals(opt)) { return Collections.singletonList(longOpt); }",
        "fixed_method": "public List<String> getMatchingOptions(String opt)\n{\n    opt = Util.stripLeadingHyphens(opt);\n    \n    List<String> matchingOpts = new ArrayList<String>();\n\n    // Check for an exact match first\n    for (String longOpt : longOpts.keySet()) {\n        if (longOpt.equals(opt)) {\n            return Collections.singletonList(longOpt);\n        }\n    }\n\n    // for partial matches\n    for (String longOpt : longOpts.keySet())\n    {\n        if (longOpt.startsWith(opt))\n        {\n            matchingOpts.add(longOpt);\n        }\n    }\n    \n    return matchingOpts;\n}",
        "diff": "+ if (longOpt.equals(opt)) { return Collections.singletonList(longOpt); }",
        "file_path": "src/main/java/org/apache/commons/cli/Options.java",
        "method_name": "getMatchingOptions",
        "class_name": "Options",
        "iteration": 1,
        "is_multi_method": false,
        "line_numbers": [
          233,
          234,
          235,
          236,
          237,
          238,
          239,
          240,
          241,
          242,
          243,
          244,
          245,
          246,
          247,
          248,
          249,
          250
        ],
        "original_code": "/**\n* Returns the options with a long name starting with the name specified.\n*\n* @param opt the partial name of the option\n* @return the options matching the partial name specified, or an empty list if none matches\n* @since 1.3\n*/\npublic List<String> getMatchingOptions(String opt)\n{\n    opt = Util.stripLeadingHyphens(opt);\n    \n    List<String> matchingOpts = new ArrayList<String>();\n\n    // for a perfect match return the single option only\n\n    for (String longOpt : longOpts.keySet())\n    {\n        if (longOpt.startsWith(opt))\n        {\n            matchingOpts.add(longOpt);\n        }\n    }\n    \n    return matchingOpts;\n}"
      },
      {
        "hypothesis": "The refined fix will first check for an exact match and store it if found. If an exact match is found, it will return a list containing only that match. If no exact match is found, it will proceed to collect all options that start with the given prefix. This ensures that the method behaves correctly for both exact and partial matches without overfitting to specific test cases.",
        "fixed_method": "public List<String> getMatchingOptions(String opt)\n{\n    if (opt == null) {\n        return Collections.emptyList();\n    }\n    \n    opt = Util.stripLeadingHyphens(opt);\n    \n    List<String> matchingOpts = new ArrayList<String>();\n    String exactMatch = null;\n\n    for (String longOpt : longOpts.keySet())\n    {\n        if (longOpt.equals(opt)) {\n            exactMatch = longOpt;\n            break;\n        } else if (longOpt.startsWith(opt))\n        {\n            matchingOpts.add(longOpt);\n        }\n    }\n    \n    if (exactMatch != null) {\n        return Collections.singletonList(exactMatch);\n    }\n    \n    return matchingOpts;\n}",
        "diff": " ",
        "file_path": "src/main/java/org/apache/commons/cli/Options.java",
        "method_name": "getMatchingOptions",
        "class_name": "Options",
        "iteration": 1,
        "is_refinement": true,
        "refinement_attempt": 1,
        "original_hypothesis": "The bug occurs because the method returns all options that start with the given prefix, causing ambiguity when there are multiple matches. To fix this, we should check for an exact match first and return it immediately if found.",
        "line_numbers": [
          233,
          234,
          235,
          236,
          237,
          238,
          239,
          240,
          241,
          242,
          243,
          244,
          245,
          246,
          247,
          248,
          249,
          250
        ]
      },
      {
        "hypothesis": "The refined fix ensures that if an exact match is found, it returns only that exact match. Otherwise, it returns all options that start with the given prefix. This addresses the overfitting by maintaining the expected behavior for both exact and prefix matches.",
        "fixed_method": "public List<String> getMatchingOptions(String opt)\n{\n    if (opt == null) {\n        return Collections.emptyList();\n    }\n    \n    opt = Util.stripLeadingHyphens(opt);\n    \n    List<String> matchingOpts = new ArrayList<String>();\n    boolean exactMatchFound = false;\n    String exactMatch = null;\n    \n    for (String longOpt : longOpts.keySet())\n    {\n        if (longOpt.equals(opt)) {\n            exactMatchFound = true;\n            exactMatch = longOpt;\n            break;\n        }\n        if (longOpt.startsWith(opt))\n        {\n            matchingOpts.add(longOpt);\n        }\n    }\n    \n    if (exactMatchFound) {\n        return Collections.singletonList(exactMatch);\n    }\n    \n    return matchingOpts;\n}",
        "diff": " ",
        "file_path": "src/main/java/org/apache/commons/cli/Options.java",
        "method_name": "getMatchingOptions",
        "class_name": "Options",
        "iteration": 1,
        "is_refinement": true,
        "refinement_attempt": 1,
        "original_hypothesis": "The bug occurs because the method returns all options that start with the given prefix, causing ambiguity when there are multiple matches. To fix this, we should first check for an exact match and return it immediately if found.",
        "line_numbers": [
          233,
          234,
          235,
          236,
          237,
          238,
          239,
          240,
          241,
          242,
          243,
          244,
          245,
          246,
          247,
          248,
          249,
          250
        ]
      }
    ]
  ],
  "iterations": 1,
  "monitor_dir": "traces/Cli-35/"
}