{
  "bug_id": "Jsoup-24",
  "success": true,
  "error": null,
  "patch": null,
  "project_path": "/tmp/d4j_Jsoup-24_1772006159",
  "patches": [
    [
      {
        "hypothesis": "The issue arises because the current implementation does not correctly handle the sequence '</scr' within a script tag comment. The parser might be incorrectly interpreting the sequence as the end of a tag, leading to the loss of a character.",
        "changes": "- r.advance();\n+ // Removed r.advance() to prevent incorrect advancement",
        "fixed_method": "void read(Tokeniser t, CharacterReader r) {\n    if (r.matchesLetter()) {\n        String name = r.consumeLetterSequence();\n        t.tagPending.appendTagName(name.toLowerCase());\n        t.dataBuffer.append(name);\n        // r.advance();\n        return;\n    }\n\n    if (t.isAppropriateEndTagToken() && !r.isEmpty()) {\n        char c = r.consume();\n        switch (c) {\n            case '\\t':\n            case '\\n':\n            case '\\f':\n            case ' ':\n                t.transition(BeforeAttributeName);\n                break;\n            case '/':\n                t.transition(SelfClosingStartTag);\n                break;\n            case '>':\n                t.emitTagPending();\n                t.transition(Data);\n                break;\n            default:\n                t.dataBuffer.append(c);\n                anythingElse(t, r);\n                break;\n        }\n    } else {\n        anythingElse(t, r);\n    }\n}",
        "diff": "- r.advance();\n+ // Removed r.advance() to prevent incorrect advancement",
        "file_path": "src/main/java/org/jsoup/parser/TokeniserState.java",
        "method_name": "read",
        "class_name": "TokeniserState",
        "iteration": 1,
        "is_multi_method": false,
        "line_numbers": [
          553,
          554,
          555,
          556,
          557,
          558,
          559,
          560,
          561,
          562,
          563,
          564,
          565,
          566,
          567,
          568,
          569,
          570,
          571,
          572,
          573,
          574,
          575,
          576,
          577,
          578,
          579,
          580,
          581,
          582,
          583,
          584,
          585,
          586
        ],
        "original_code": "// consuming to EOF; break out here\nvoid read(Tokeniser t, CharacterReader r) {\n    if (r.matchesLetter()) {\n        String name = r.consumeLetterSequence();\n        t.tagPending.appendTagName(name.toLowerCase());\n        t.dataBuffer.append(name);\n        r.advance();\n        return;\n    }\n\n    if (t.isAppropriateEndTagToken() && !r.isEmpty()) {\n        char c = r.consume();\n        switch (c) {\n            case '\\t':\n            case '\\n':\n            case '\\f':\n            case ' ':\n                t.transition(BeforeAttributeName);\n                break;\n            case '/':\n                t.transition(SelfClosingStartTag);\n                break;\n            case '>':\n                t.emitTagPending();\n                t.transition(Data);\n                break;\n            default:\n                t.dataBuffer.append(c);\n                anythingElse(t, r);\n                break;\n        }\n    } else {\n        anythingElse(t, r);\n    }\n}"
      },
      {
        "hypothesis": "The issue seems to be related to how characters are consumed and appended to the data buffer. Specifically, it appears that a character might be incorrectly consumed or not appended as expected, leading to a missing character in the output.",
        "changes": "- r.advance();\n+ // r.advance(); // Removed this line to prevent advancing the reader prematurely",
        "fixed_method": "void read(Tokeniser t, CharacterReader r) {\n    if (r.matchesLetter()) {\n        String name = r.consumeLetterSequence();\n        t.tagPending.appendTagName(name.toLowerCase());\n        t.dataBuffer.append(name);\n        // r.advance(); // Removed this line to prevent advancing the reader prematurely\n        return;\n    }\n\n    if (t.isAppropriateEndTagToken() && !r.isEmpty()) {\n        char c = r.consume();\n        switch (c) {\n            case '\\t':\n            case '\\n':\n            case '\\f':\n            case ' ':\n                t.transition(BeforeAttributeName);\n                break;\n            case '/':\n                t.transition(SelfClosingStartTag);\n                break;\n            case '>':\n                t.emitTagPending();\n                t.transition(Data);\n                break;\n            default:\n                t.dataBuffer.append(c);\n                anythingElse(t, r);\n                break;\n        }\n    } else {\n        anythingElse(t, r);\n    }\n}",
        "diff": "- r.advance();\n+ // r.advance(); // Removed this line to prevent advancing the reader prematurely",
        "file_path": "src/main/java/org/jsoup/parser/TokeniserState.java",
        "method_name": "read",
        "class_name": "TokeniserState",
        "iteration": 1,
        "is_multi_method": false,
        "line_numbers": [
          553,
          554,
          555,
          556,
          557,
          558,
          559,
          560,
          561,
          562,
          563,
          564,
          565,
          566,
          567,
          568,
          569,
          570,
          571,
          572,
          573,
          574,
          575,
          576,
          577,
          578,
          579,
          580,
          581,
          582,
          583,
          584,
          585,
          586
        ],
        "original_code": "// consuming to EOF; break out here\nvoid read(Tokeniser t, CharacterReader r) {\n    if (r.matchesLetter()) {\n        String name = r.consumeLetterSequence();\n        t.tagPending.appendTagName(name.toLowerCase());\n        t.dataBuffer.append(name);\n        r.advance();\n        return;\n    }\n\n    if (t.isAppropriateEndTagToken() && !r.isEmpty()) {\n        char c = r.consume();\n        switch (c) {\n            case '\\t':\n            case '\\n':\n            case '\\f':\n            case ' ':\n                t.transition(BeforeAttributeName);\n                break;\n            case '/':\n                t.transition(SelfClosingStartTag);\n                break;\n            case '>':\n                t.emitTagPending();\n                t.transition(Data);\n                break;\n            default:\n                t.dataBuffer.append(c);\n                anythingElse(t, r);\n                break;\n        }\n    } else {\n        anythingElse(t, r);\n    }\n}"
      },
      {
        "hypothesis": "The issue arises because the method does not correctly handle characters within script tags, particularly when encountering a closing bracket followed by a quote. The current implementation might be incorrectly advancing the reader or appending characters inappropriately.",
        "changes": "- r.advance(); // Removed unnecessary advance call\n+ // Ensure that the reader does not advance unnecessarily and handles script content correctly",
        "fixed_method": "void read(Tokeniser t, CharacterReader r) {\n    if (r.matchesLetter()) {\n        String name = r.consumeLetterSequence();\n        t.tagPending.appendTagName(name.toLowerCase());\n        t.dataBuffer.append(name);\n        // Removed unnecessary advance call\n        return;\n    }\n\n    if (t.isAppropriateEndTagToken() && !r.isEmpty()) {\n        char c = r.consume();\n        switch (c) {\n            case '\\t':\n            case '\\n':\n            case '\\f':\n            case ' ':\n                t.transition(BeforeAttributeName);\n                break;\n            case '/':\n                t.transition(SelfClosingStartTag);\n                break;\n            case '>':\n                t.emitTagPending();\n                t.transition(Data);\n                break;\n            default:\n                t.dataBuffer.append(c);\n                anythingElse(t, r);\n                break;\n        }\n    } else {\n        anythingElse(t, r);\n    }\n}",
        "diff": "- r.advance(); // Removed unnecessary advance call\n+ // Ensure that the reader does not advance unnecessarily and handles script content correctly",
        "file_path": "src/main/java/org/jsoup/parser/TokeniserState.java",
        "method_name": "read",
        "class_name": "TokeniserState",
        "iteration": 1,
        "is_multi_method": false,
        "line_numbers": [
          553,
          554,
          555,
          556,
          557,
          558,
          559,
          560,
          561,
          562,
          563,
          564,
          565,
          566,
          567,
          568,
          569,
          570,
          571,
          572,
          573,
          574,
          575,
          576,
          577,
          578,
          579,
          580,
          581,
          582,
          583,
          584,
          585,
          586
        ],
        "original_code": "// consuming to EOF; break out here\nvoid read(Tokeniser t, CharacterReader r) {\n    if (r.matchesLetter()) {\n        String name = r.consumeLetterSequence();\n        t.tagPending.appendTagName(name.toLowerCase());\n        t.dataBuffer.append(name);\n        r.advance();\n        return;\n    }\n\n    if (t.isAppropriateEndTagToken() && !r.isEmpty()) {\n        char c = r.consume();\n        switch (c) {\n            case '\\t':\n            case '\\n':\n            case '\\f':\n            case ' ':\n                t.transition(BeforeAttributeName);\n                break;\n            case '/':\n                t.transition(SelfClosingStartTag);\n                break;\n            case '>':\n                t.emitTagPending();\n                t.transition(Data);\n                break;\n            default:\n                t.dataBuffer.append(c);\n                anythingElse(t, r);\n                break;\n        }\n    } else {\n        anythingElse(t, r);\n    }\n}"
      }
    ]
  ],
  "iterations": 1,
  "monitor_dir": "traces/Jsoup-24/"
}